{
    "success": true,
    "data":[
        {
            "id": 5,
            "title": "渗透某福利网站",
            "desc": "0*00前言 故事的起因: 然后 没有想到我为了一张SSC安全峰会的门票，义无反顾的走进上了一条不归路，不是一般的坑... 0*01信息收集 首...",
            "imgUrl": "//upload-images.jianshu.io/upload_images/48820-2eb6e5b4bba9dcd6?imageMogr2/auto-orient/strip|imageView2/1/w/300/h/240"},
        {
            "id": 6,
            "title": "渗透某福利网站",
            "desc": "0*00前言 故事的起因: 然后 没有想到我为了一张SSC安全峰会的门票，义无反顾的走进上了一条不归路，不是一般的坑... 0*01信息收集 首...",
            "imgUrl": "//upload-images.jianshu.io/upload_images/48820-2eb6e5b4bba9dcd6?imageMogr2/auto-orient/strip|imageView2/1/w/300/h/240"},
        {
            "id": 7,
            "title": "渗透某福利网站",
            "desc": "0*00前言 故事的起因: 然后 没有想到我为了一张SSC安全峰会的门票，义无反顾的走进上了一条不归路，不是一般的坑... 0*01信息收集 首...",
            "imgUrl": "//upload-images.jianshu.io/upload_images/48820-2eb6e5b4bba9dcd6?imageMogr2/auto-orient/strip|imageView2/1/w/300/h/240"},
        {
            "id": 8,
            "title": "渗透某福利网站",
            "desc": "0*00前言 故事的起因: 然后 没有想到我为了一张SSC安全峰会的门票，义无反顾的走进上了一条不归路，不是一般的坑... 0*01信息收集 首...",
            "imgUrl": "//upload-images.jianshu.io/upload_images/48820-2eb6e5b4bba9dcd6?imageMogr2/auto-orient/strip|imageView2/1/w/300/h/240"}
    ]
}